redisexport/__init__.py
redisexport/main.py
redis_export-0.3.1.dist-info/METADATA
redis_export-0.3.1.dist-info/WHEEL
redis_export-0.3.1.dist-info/entry_points.txt
redis_export-0.3.1.dist-info/top_level.txt
redis_export-0.3.1.dist-info/RECORD
