Metadata-Version: 2.1
Name: redis-export
Version: 0.3.1
Summary: Export redis keys with a prefix or matching a pattern, import from exported file
Home-page: https://pypi.org/project/redis-export/
Author: Yuanle Song
Author-email: sylecn@gmail.com
Maintainer: Yuanle Song
Maintainer-email: sylecn@gmail.com
License: GPLv3+
Classifier: Development Status :: 4 - Beta
Classifier: License :: OSI Approved :: GNU General Public License (GPL)
Classifier: License :: OSI Approved :: GNU General Public License v3 or later (GPLv3+)
Classifier: Programming Language :: Python :: 3.5
Classifier: Programming Language :: Python :: 3.6
Classifier: Programming Language :: Python :: 3.7
Classifier: Programming Language :: Python :: 3.8
Classifier: Programming Language :: Python :: 3.9
Requires-Dist: redis
